{
  "Unset": "Unset",
  "Blanche": "Blanche",
  "Candela": "Candela",
  "Spark": "Spark",
  "Grunt (Male)": "undefined (undefined)",
  "Grunt (Female)": "undefined (undefined)",
  "Bug - Grunt (Female)": "undefined (undefined)",
  "Bug - Grunt (Male)": "undefined (undefined)",
  "Dark - Grunt (Female)": "undefined (undefined)",
  "Dark - Grunt (Male)": "undefined (undefined)",
  "Dragon - Grunt (Female)": "undefined (undefined)",
  "Dragon - Grunt (Male)": "undefined (undefined)",
  "Fairy - Grunt (Female)": "undefined (undefined)",
  "Fairy - Grunt (Male)": "undefined (undefined)",
  "Fighting - Grunt (Female)": "undefined (undefined)",
  "Fighting - Grunt (Male)": "undefined (undefined)",
  "Fire - Grunt (Female)": "undefined (undefined)",
  "Fire - Grunt (Male)": "undefined (undefined)",
  "Flying - Grunt (Female)": "undefined (undefined)",
  "Flying - Grunt (Male)": "undefined (undefined)",
  "Grass - Grunt (Female)": "undefined (undefined)",
  "Grass - Grunt (Male)": "undefined (undefined)",
  "Ground - Grunt (Female)": "undefined (undefined)",
  "Ground - Grunt (Male)": "undefined (undefined)",
  "Ice - Grunt (Female)": "undefined (undefined)",
  "Ice - Grunt (Male)": "undefined (undefined)",
  "Steel - Grunt (Female)": "undefined (undefined)",
  "Steel - Grunt (Male)": "undefined (undefined)",
  "Normal - Grunt (Female)": "undefined (undefined)",
  "Normal - Grunt (Male)": "undefined (undefined)",
  "Poison - Grunt (Female)": "undefined (undefined)",
  "Poison - Grunt (Male)": "undefined (undefined)",
  "Psychic - Grunt (Female)": "undefined (undefined)",
  "Psychic - Grunt (Male)": "undefined (undefined)",
  "Rock - Grunt (Female)": "undefined (undefined)",
  "Rock - Grunt (Male)": "undefined (undefined)",
  "Water - Grunt (Female)": "undefined (undefined)",
  "Water - Grunt (Male)": "undefined (undefined)",
  "Player Team Leader": "Player Team Leader",
  "Leader Cliff": "Cliff",
  "Leader Arlo": "Arlo",
  "Leader Sierra": "Sierra",
  "Giovanni": "Giovanni",
  "Decoy Grunt (Male)": "undefined (undefined)",
  "Decoy Grunt (Female)": "undefined (undefined)",
  "Ghost - Grunt (Female)": "undefined (undefined)",
  "Ghost - Grunt (Male)": "undefined (undefined)",
  "Electric - Grunt (Female)": "undefined (undefined)",
  "Electric - Grunt (Male)": "undefined (undefined)",
  "Jessie": "Jessie",
  "James": "James",
  "Willow": "Willow",
  "Willowb": "Willowb",
  "LenTao9": "NPC 0",
  "oneslapguy": "NPC 1",
  "DieCurryWurst": "NPC 3",
  "Juanevoli": "NPC 4",
  "Trainer yournameNPC05": "NPC 5",
  "CashmereFeline": "NPC 6",
  "enjoyryde": "NPC 7",
  "Trainer yournameNPC08": "NPC 8",
  "Telli997": "NPC 9",
  "malibuleo": "NPC 10",
  "NPC Blanche": "NPC Blanche",
  "NPC Candela": "NPC Candela",
  "NPC Spark": "NPC Spark",
  "NPC 11": "NPC 11",
  "NPC 12": "NPC 12",
  "NPC 13": "NPC 13",
  "NPC 14": "NPC 14",
  "NPC 15": "NPC 15",
  "NPC 16": "NPC 16",
  "NPC 17": "NPC 17",
  "NPC 18": "NPC 18",
  "NPC 19": "NPC 19",
  "NPC 20": "NPC 20",
  "None": "無",
  "Grunt ♂": "undefined ♂",
  "Grunt ♀": "undefined ♀",
  "Bug ♀": "undefined ♀",
  "Bug ♂": "undefined ♂",
  "Dark ♀": "undefined ♀",
  "Dark ♂": "undefined ♂",
  "Dragon ♀": "undefined ♀",
  "Dragon ♂": "undefined ♂",
  "Fairy ♀": "undefined ♀",
  "Fairy ♂": "undefined ♂",
  "Fighting ♀": "undefined ♀",
  "Fighting ♂": "undefined ♂",
  "Fire ♀": "undefined ♀",
  "Fire ♂": "undefined ♂",
  "Flying ♀": "undefined ♀",
  "Flying ♂": "undefined ♂",
  "Grass ♀": "undefined ♀",
  "Grass ♂": "undefined ♂",
  "Ground ♀": "undefined ♀",
  "Ground ♂": "undefined ♂",
  "Ice ♀": "undefined ♀",
  "Ice ♂": "undefined ♂",
  "Steel ♀": "undefined ♀",
  "Steel ♂": "undefined ♂",
  "Normal ♀": "undefined ♀",
  "Normal ♂": "undefined ♂",
  "Poison ♀": "undefined ♀",
  "Poison ♂": "undefined ♂",
  "Psychic ♀": "undefined ♀",
  "Psychic ♂": "undefined ♂",
  "Rock ♀": "undefined ♀",
  "Rock ♂": "undefined ♂",
  "Water ♀": "undefined ♀",
  "Water ♂": "undefined ♂",
  "Decoy Grunt ♂": "undefined ♂",
  "Decoy Grunt ♀": "undefined ♀",
  "Ghost ♀": "undefined ♀",
  "Ghost ♂": "undefined ♂",
  "Electric ♀": "undefined ♀",
  "Electric ♂": "undefined ♂"
}