{
  "form_0": "form_0",
  "form_27": "!",
  "form_28": "?",
  "form_29": "Normal",
  "form_30": "Solaire",
  "form_31": "Eau de pluie",
  "form_32": "Blizzard",
  "form_33": "Normal",
  "form_34": "Attaque",
  "form_35": "Défense",
  "form_36": "Vitesse",
  "form_37": "01",
  "form_38": "02",
  "form_39": "03",
  "form_40": "04",
  "form_41": "05",
  "form_42": "06",
  "form_43": "07",
  "form_44": "08",
  "form_45": "Normal",
  "form_46": "Alola",
  "form_47": "Normal",
  "form_48": "Alola",
  "form_49": "Normal",
  "form_50": "Alola",
  "form_51": "Normal",
  "form_52": "Alola",
  "form_53": "Normal",
  "form_54": "Alola",
  "form_55": "Normal",
  "form_56": "Alola",
  "form_57": "Normal",
  "form_58": "Alola",
  "form_59": "Normal",
  "form_60": "Alola",
  "form_61": "Normal",
  "form_62": "Alola",
  "form_63": "Normal",
  "form_64": "Alola",
  "form_65": "Normal",
  "form_66": "Alola",
  "form_67": "Normal",
  "form_68": "Alola",
  "form_69": "Normal",
  "form_70": "Alola",
  "form_71": "Normal",
  "form_72": "Alola",
  "form_73": "Normal",
  "form_74": "Alola",
  "form_75": "Normal",
  "form_76": "Alola",
  "form_77": "Normal",
  "form_78": "Alola",
  "form_79": "Normal",
  "form_80": "Alola",
  "form_81": "Normal",
  "form_82": "Motisma Froid",
  "form_83": "Motisma Hélice",
  "form_84": "Motisma Tonte",
  "form_85": "Motisma Lavage",
  "form_86": "Motisma Chaleur",
  "form_87": "Plante",
  "form_88": "Cape Sable",
  "form_89": "Cape Déchet",
  "form_90": "Forme Alternative",
  "form_91": "Forme Originelle",
  "form_92": "Forme Céleste",
  "form_93": "Forme Terrestre",
  "form_94": "Temps Couvert",
  "form_95": "Temps Ensoleillé",
  "form_96": "Mer Occident",
  "form_97": "Mer Orient",
  "form_98": "Mer Occident",
  "form_99": "Mer Orient",
  "form_100": "Normal",
  "form_101": "Combat",
  "form_102": "Vol",
  "form_103": "Poison",
  "form_104": "Sol",
  "form_105": "Roche",
  "form_106": "Insecte",
  "form_107": "Spectre",
  "form_108": "Acier",
  "form_109": "Feu",
  "form_110": "Eau",
  "form_111": "Plante",
  "form_112": "Électrik",
  "form_113": "Psy",
  "form_114": "Glace",
  "form_115": "Dragon",
  "form_116": "Ténèbres",
  "form_117": "Fée",
  "form_118": "Cape Plante",
  "form_119": "Cape Sable",
  "form_120": "Cape Déchet",
  "form_121": "09",
  "form_122": "10",
  "form_123": "11",
  "form_124": "12",
  "form_125": "13",
  "form_126": "14",
  "form_127": "15",
  "form_128": "16",
  "form_129": "17",
  "form_130": "18",
  "form_131": "19",
  "form_132": "20",
  "form_133": "Armure",
  "form_135": "Normal",
  "form_136": "Motif Rouge",
  "form_137": "Motif Bleu",
  "form_138": "Standard",
  "form_139": "Zen",
  "form_140": "Forme Avatar",
  "form_141": "Forme Totémique",
  "form_142": "Forme Avatar",
  "form_143": "Forme Totémique",
  "form_144": "Forme Avatar",
  "form_145": "Forme Totémique",
  "form_146": "Normal",
  "form_147": "Kyurem Noir",
  "form_148": "Kyurem Blanc",
  "form_149": "Aspect Normal",
  "form_150": "Resolute",
  "form_151": "Forme Chant",
  "form_152": "Pirouette",
  "form_153": "Obscur",
  "form_154": "Purifié",
  "form_155": "Obscur",
  "form_156": "Purifié",
  "form_157": "Normal",
  "form_158": "Obscur",
  "form_159": "Purifié",
  "form_160": "Normal",
  "form_161": "Obscur",
  "form_162": "Purifié",
  "form_163": "Normal",
  "form_164": "Obscur",
  "form_165": "Purifié",
  "form_166": "Normal",
  "form_167": "Obscur",
  "form_168": "Purifié",
  "form_169": "Normal",
  "form_170": "Obscur",
  "form_171": "Purifié",
  "form_172": "Normal",
  "form_173": "Obscur",
  "form_174": "Purifié",
  "form_175": "Normal",
  "form_176": "Obscur",
  "form_177": "Purifié",
  "form_178": "Normal",
  "form_179": "Obscur",
  "form_180": "Purifié",
  "form_181": "Normal",
  "form_182": "Obscur",
  "form_183": "Purifié",
  "form_184": "Normal",
  "form_185": "Obscur",
  "form_186": "Purifié",
  "form_187": "Normal",
  "form_188": "Obscur",
  "form_189": "Purifié",
  "form_190": "Normal",
  "form_191": "Obscur",
  "form_192": "Purifié",
  "form_193": "Normal",
  "form_194": "Obscur",
  "form_195": "Purifié",
  "form_196": "Normal",
  "form_197": "Obscur",
  "form_198": "Purifié",
  "form_199": "Normal",
  "form_200": "Obscur",
  "form_201": "Purifié",
  "form_202": "Normal",
  "form_203": "Obscur",
  "form_204": "Purifié",
  "form_205": "Normal",
  "form_206": "Obscur",
  "form_207": "Purifié",
  "form_208": "Normal",
  "form_209": "Obscur",
  "form_210": "Purifié",
  "form_211": "Normal",
  "form_212": "Obscur",
  "form_213": "Purifié",
  "form_214": "Normal",
  "form_215": "Obscur",
  "form_216": "Purifié",
  "form_217": "Normal",
  "form_218": "Obscur",
  "form_219": "Purifié",
  "form_220": "Obscur",
  "form_221": "Purifié",
  "form_222": "Obscur",
  "form_223": "Purifié",
  "form_224": "Normal",
  "form_225": "Obscur",
  "form_226": "Purifié",
  "form_227": "Obscur",
  "form_228": "Purifié",
  "form_229": "Normal",
  "form_230": "Obscur",
  "form_231": "Purifié",
  "form_232": "Normal",
  "form_233": "Obscur",
  "form_234": "Purifié",
  "form_235": "Normal",
  "form_236": "Obscur",
  "form_237": "Purifié",
  "form_238": "Normal",
  "form_239": "Obscur",
  "form_240": "Purifié",
  "form_241": "Normal",
  "form_242": "Obscur",
  "form_243": "Purifié",
  "form_244": "Normal",
  "form_245": "Obscur",
  "form_246": "Purifié",
  "form_247": "Normal",
  "form_248": "Obscur",
  "form_249": "Purifié",
  "form_250": "Normal",
  "form_251": "Obscur",
  "form_252": "Purifié",
  "form_253": "Normal",
  "form_254": "Obscur",
  "form_255": "Purifié",
  "form_256": "Normal",
  "form_257": "Obscur",
  "form_258": "Purifié",
  "form_259": "Normal",
  "form_260": "Obscur",
  "form_261": "Purifié",
  "form_262": "Normal",
  "form_263": "Obscur",
  "form_264": "Purifié",
  "form_265": "Normal",
  "form_266": "Obscur",
  "form_267": "Purifié",
  "form_268": "Normal",
  "form_269": "Obscur",
  "form_270": "Purifié",
  "form_271": "Normal",
  "form_272": "Obscur",
  "form_273": "Purifié",
  "form_274": "Normal",
  "form_275": "Obscur",
  "form_276": "Purifié",
  "form_277": "Normal",
  "form_278": "Obscur",
  "form_279": "Purifié",
  "form_280": "Normal",
  "form_281": "Obscur",
  "form_282": "Purifié",
  "form_283": "Normal",
  "form_284": "Obscur",
  "form_285": "Purifié",
  "form_286": "Normal",
  "form_287": "Obscur",
  "form_288": "Purifié",
  "form_289": "Normal",
  "form_290": "Obscur",
  "form_291": "Purifié",
  "form_292": "Normal",
  "form_293": "Obscur",
  "form_294": "Purifié",
  "form_295": "Normal",
  "form_296": "Obscur",
  "form_297": "Purifié",
  "form_298": "Normal",
  "form_299": "Obscur",
  "form_300": "Purifié",
  "form_301": "Normal",
  "form_302": "Obscur",
  "form_303": "Purifié",
  "form_304": "Normal",
  "form_305": "Obscur",
  "form_306": "Purifié",
  "form_307": "Normal",
  "form_308": "Obscur",
  "form_309": "Purifié",
  "form_310": "Normal",
  "form_311": "Obscur",
  "form_312": "Purifié",
  "form_313": "Normal",
  "form_314": "Obscur",
  "form_315": "Purifié",
  "form_316": "Normal",
  "form_317": "Obscur",
  "form_318": "Purifié",
  "form_319": "Normal",
  "form_320": "Obscur",
  "form_321": "Purifié",
  "form_322": "Normal",
  "form_323": "Obscur",
  "form_324": "Purifié",
  "form_585": "Forme Printemps",
  "form_586": "Forme Été",
  "form_587": "Forme Automne",
  "form_588": "Forme Hiver",
  "form_589": "Forme Printemps",
  "form_590": "Forme Été",
  "form_591": "Forme Automne",
  "form_592": "Forme Hiver",
  "form_593": "Normal",
  "form_594": "Module Choc",
  "form_595": "Module Pyro",
  "form_596": "Module Cryo",
  "form_597": "Module Aqua",
  "form_598": "Normal",
  "form_599": "Noevolve",
  "form_600": "Normal",
  "form_601": "Noevolve",
  "form_602": "Normal",
  "form_603": "Noevolve",
  "form_604": "Noevolve",
  "form_605": "Noevolve",
  "form_606": "Noevolve",
  "form_607": "Noevolve",
  "form_608": "Noevolve",
  "form_609": "Noevolve",
  "form_610": "Normal",
  "form_611": "Obscur",
  "form_612": "Purifié",
  "form_613": "Normal",
  "form_614": "Obscur",
  "form_615": "Purifié",
  "form_616": "Normal",
  "form_617": "Obscur",
  "form_618": "Purifié",
  "form_619": "Normal",
  "form_620": "Obscur",
  "form_621": "Purifié",
  "form_622": "Normal",
  "form_623": "Obscur",
  "form_624": "Purifié",
  "form_625": "Normal",
  "form_626": "Obscur",
  "form_627": "Purifié",
  "form_628": "Normal",
  "form_629": "Obscur",
  "form_630": "Purifié",
  "form_631": "Normal",
  "form_632": "Obscur",
  "form_633": "Purifié",
  "form_634": "Normal",
  "form_635": "Obscur",
  "form_636": "Purifié",
  "form_637": "Normal",
  "form_638": "Obscur",
  "form_639": "Purifié",
  "form_640": "Normal",
  "form_641": "Obscur",
  "form_642": "Purifié",
  "form_643": "Normal",
  "form_644": "Obscur",
  "form_645": "Purifié",
  "form_646": "Normal",
  "form_647": "Obscur",
  "form_648": "Purifié",
  "form_649": "Normal",
  "form_650": "Obscur",
  "form_651": "Purifié",
  "form_652": "Normal",
  "form_653": "Obscur",
  "form_654": "Purifié",
  "form_655": "Normal",
  "form_656": "Obscur",
  "form_657": "Purifié",
  "form_658": "Normal",
  "form_659": "Obscur",
  "form_660": "Purifié",
  "form_661": "Normal",
  "form_662": "Obscur",
  "form_663": "Purifié",
  "form_664": "Normal",
  "form_665": "Obscur",
  "form_666": "Purifié",
  "form_667": "Normal",
  "form_668": "Obscur",
  "form_669": "Purifié",
  "form_670": "Normal",
  "form_671": "Obscur",
  "form_672": "Purifié",
  "form_673": "Obscur",
  "form_674": "Purifié",
  "form_675": "Obscur",
  "form_676": "Purifié",
  "form_677": "Normal",
  "form_678": "Obscur",
  "form_679": "Purifié",
  "form_680": "Normal",
  "form_681": "Obscur",
  "form_682": "Purifié",
  "form_683": "Normal",
  "form_684": "Obscur",
  "form_685": "Purifié",
  "form_686": "Obscur",
  "form_687": "Purifié",
  "form_688": "Normal",
  "form_689": "Obscur",
  "form_690": "Purifié",
  "form_691": "Normal",
  "form_692": "Obscur",
  "form_693": "Purifié",
  "form_694": "Normal",
  "form_695": "Obscur",
  "form_696": "Purifié",
  "form_697": "Normal",
  "form_698": "Obscur",
  "form_699": "Purifié",
  "form_700": "Normal",
  "form_701": "Obscur",
  "form_702": "Purifié",
  "form_703": "Normal",
  "form_704": "Obscur",
  "form_705": "Purifié",
  "form_706": "Normal",
  "form_707": "Obscur",
  "form_708": "Purifié",
  "form_709": "Obscur",
  "form_710": "Purifié",
  "form_711": "Obscur",
  "form_712": "Purifié",
  "form_713": "Normal",
  "form_714": "Obscur",
  "form_715": "Purifié",
  "form_716": "Normal",
  "form_717": "Obscur",
  "form_718": "Purifié",
  "form_719": "Normal",
  "form_720": "Obscur",
  "form_721": "Purifié",
  "form_722": "Normal",
  "form_723": "Obscur",
  "form_724": "Purifié",
  "form_725": "Obscur",
  "form_726": "Purifié",
  "form_727": "Obscur",
  "form_728": "Purifié",
  "form_729": "Normal",
  "form_730": "Obscur",
  "form_731": "Purifié",
  "form_732": "Obscur",
  "form_733": "Purifié",
  "form_734": "Normal",
  "form_735": "Obscur",
  "form_736": "Purifié",
  "form_737": "Normal",
  "form_738": "Obscur",
  "form_739": "Purifié",
  "form_740": "Normal",
  "form_741": "Obscur",
  "form_742": "Purifié",
  "form_743": "Normal",
  "form_744": "Obscur",
  "form_745": "Purifié",
  "form_746": "Normal",
  "form_747": "Obscur",
  "form_748": "Purifié",
  "form_749": "Normal",
  "form_750": "Obscur",
  "form_751": "Purifié",
  "form_752": "Normal",
  "form_753": "Obscur",
  "form_754": "Purifié",
  "form_755": "Normal",
  "form_756": "Obscur",
  "form_757": "Purifié",
  "form_758": "Normal",
  "form_759": "Obscur",
  "form_760": "Purifié",
  "form_761": "Normal",
  "form_762": "Obscur",
  "form_763": "Purifié",
  "form_764": "Normal",
  "form_765": "Obscur",
  "form_766": "Purifié",
  "form_767": "Normal",
  "form_768": "Obscur",
  "form_769": "Purifié",
  "form_770": "Normal",
  "form_771": "Obscur",
  "form_772": "Purifié",
  "form_773": "Normal",
  "form_774": "Obscur",
  "form_775": "Purifié",
  "form_776": "Normal",
  "form_777": "Obscur",
  "form_778": "Purifié",
  "form_779": "Normal",
  "form_780": "Obscur",
  "form_781": "Purifié",
  "form_782": "Normal",
  "form_783": "Obscur",
  "form_784": "Purifié",
  "form_785": "Normal",
  "form_786": "Obscur",
  "form_787": "Purifié",
  "form_788": "Normal",
  "form_789": "Obscur",
  "form_790": "Purifié",
  "form_791": "Normal",
  "form_792": "Obscur",
  "form_793": "Purifié",
  "form_794": "Normal",
  "form_795": "Obscur",
  "form_796": "Purifié",
  "form_797": "Normal",
  "form_798": "Obscur",
  "form_799": "Purifié",
  "form_800": "Normal",
  "form_801": "Obscur",
  "form_802": "Purifié",
  "form_803": "Normal",
  "form_804": "Obscur",
  "form_805": "Purifié",
  "form_806": "Normal",
  "form_807": "Obscur",
  "form_808": "Purifié",
  "form_809": "Normal",
  "form_810": "Obscur",
  "form_811": "Purifié",
  "form_812": "Normal",
  "form_813": "Obscur",
  "form_814": "Purifié",
  "form_815": "Normal",
  "form_816": "Obscur",
  "form_817": "Purifié",
  "form_818": "Normal",
  "form_819": "Obscur",
  "form_820": "Purifié",
  "form_821": "Normal",
  "form_822": "Obscur",
  "form_823": "Purifié",
  "form_824": "Normal",
  "form_825": "Obscur",
  "form_826": "Purifié",
  "form_827": "Normal",
  "form_828": "Obscur",
  "form_829": "Purifié",
  "form_830": "Normal",
  "form_831": "Obscur",
  "form_832": "Purifié",
  "form_833": "Normal",
  "form_834": "Obscur",
  "form_835": "Purifié",
  "form_836": "Normal",
  "form_837": "Obscur",
  "form_838": "Purifié",
  "form_839": "Normal",
  "form_840": "Obscur",
  "form_841": "Purifié",
  "form_842": "Obscur",
  "form_843": "Purifié",
  "form_844": "Obscur",
  "form_845": "Purifié",
  "form_846": "Normal",
  "form_847": "Obscur",
  "form_848": "Purifié",
  "form_849": "Normal",
  "form_850": "Obscur",
  "form_851": "Purifié",
  "form_852": "Normal",
  "form_853": "Obscur",
  "form_854": "Purifié",
  "form_855": "Normal",
  "form_856": "Obscur",
  "form_857": "Purifié",
  "form_858": "Normal",
  "form_859": "Obscur",
  "form_860": "Purifié",
  "form_861": "Normal",
  "form_862": "Obscur",
  "form_863": "Purifié",
  "form_864": "Normal",
  "form_865": "Obscur",
  "form_866": "Purifié",
  "form_867": "Normal",
  "form_868": "Obscur",
  "form_869": "Purifié",
  "form_870": "Normal",
  "form_871": "Obscur",
  "form_872": "Purifié",
  "form_873": "Normal",
  "form_874": "Obscur",
  "form_875": "Purifié",
  "form_876": "Normal",
  "form_877": "Obscur",
  "form_878": "Purifié",
  "form_879": "Normal",
  "form_880": "Obscur",
  "form_881": "Purifié",
  "form_882": "Obscur",
  "form_883": "Purifié",
  "form_884": "Obscur",
  "form_885": "Purifié",
  "form_886": "Obscur",
  "form_887": "Purifié",
  "form_888": "Normal",
  "form_889": "Obscur",
  "form_890": "Purifié",
  "form_891": "Normal",
  "form_892": "Obscur",
  "form_893": "Purifié",
  "form_894": "Automne 2019",
  "form_895": "Automne 2019",
  "form_896": "Automne 2019",
  "form_897": "Automne 2019",
  "form_898": "Normal",
  "form_899": "Obscur",
  "form_900": "Purifié",
  "form_901": "Vs 2019",
  "form_902": "Normal",
  "form_903": "Obscur",
  "form_904": "Purifié",
  "form_905": "Normal",
  "form_906": "Obscur",
  "form_907": "Purifié",
  "form_908": "Normal",
  "form_909": "Obscur",
  "form_910": "Purifié",
  "form_911": "Normal",
  "form_912": "Obscur",
  "form_913": "Purifié",
  "form_914": "Normal",
  "form_915": "Obscur",
  "form_916": "Purifié",
  "form_917": "Normal",
  "form_918": "Obscur",
  "form_919": "Purifié",
  "form_920": "Normal",
  "form_921": "Obscur",
  "form_922": "Purifié",
  "form_923": "Normal",
  "form_924": "Obscur",
  "form_925": "Purifié",
  "form_926": "Normal",
  "form_927": "Obscur",
  "form_928": "Purifié",
  "form_929": "Normal",
  "form_930": "Obscur",
  "form_931": "Purifié",
  "form_932": "Normal",
  "form_933": "Obscur",
  "form_934": "Purifié",
  "form_935": "Normal",
  "form_936": "Obscur",
  "form_937": "Purifié",
  "form_938": "Normal",
  "form_939": "Obscur",
  "form_940": "Purifié",
  "form_941": "Normal",
  "form_942": "Obscur",
  "form_943": "Purifié",
  "form_944": "Galarian",
  "form_945": "Normal",
  "form_946": "Galarian",
  "form_947": "Normal",
  "form_948": "Galarian",
  "form_949": "Clone 2019",
  "form_950": "Clone 2019",
  "form_951": "Clone 2019",
  "form_952": "Clone 2019",
  "form_953": "Normal",
  "form_954": "Obscur",
  "form_955": "Purifié",
  "form_956": "Normal",
  "form_957": "Obscur",
  "form_958": "Purifié",
  "form_959": "Normal",
  "form_960": "Obscur",
  "form_961": "Purifié",
  "form_962": "Normal",
  "form_963": "Obscur",
  "form_964": "Purifié",
  "form_965": "Normal",
  "form_966": "Obscur",
  "form_967": "Purifié",
  "form_968": "Normal",
  "form_969": "Obscur",
  "form_970": "Purifié",
  "form_971": "Normal",
  "form_972": "Obscur",
  "form_973": "Purifié",
  "form_974": "Normal",
  "form_975": "Obscur",
  "form_976": "Purifié",
  "form_977": "Obscur",
  "form_978": "Purifié",
  "form_979": "Obscur",
  "form_980": "Purifié",
  "form_981": "Normal",
  "form_982": "Obscur",
  "form_983": "Purifié",
  "form_984": "Normal",
  "form_985": "Obscur",
  "form_986": "Purifié",
  "form_987": "Normal",
  "form_988": "Obscur",
  "form_989": "Purifié",
  "form_990": "Normal",
  "form_991": "Obscur",
  "form_992": "Purifié",
  "form_993": "Normal",
  "form_994": "Obscur",
  "form_995": "Purifié",
  "form_996": "Normal",
  "form_997": "Obscur",
  "form_998": "Purifié",
  "form_999": "Normal",
  "form_1000": "Obscur",
  "form_1001": "Purifié",
  "form_1002": "Normal",
  "form_1003": "Obscur",
  "form_1004": "Purifié",
  "form_1005": "Normal",
  "form_1006": "Obscur",
  "form_1007": "Purifié",
  "form_1008": "Normal",
  "form_1009": "Obscur",
  "form_1010": "Purifié",
  "form_1011": "Normal",
  "form_1012": "Obscur",
  "form_1013": "Purifié",
  "form_1014": "Normal",
  "form_1015": "Obscur",
  "form_1016": "Purifié",
  "form_1017": "Normal",
  "form_1018": "Obscur",
  "form_1019": "Purifié",
  "form_1020": "Normal",
  "form_1021": "Obscur",
  "form_1022": "Purifié",
  "form_1023": "Normal",
  "form_1024": "Obscur",
  "form_1025": "Purifié",
  "form_1026": "Normal",
  "form_1027": "Obscur",
  "form_1028": "Purifié",
  "form_1029": "Normal",
  "form_1030": "Obscur",
  "form_1031": "Purifié",
  "form_1032": "Normal",
  "form_1033": "Obscur",
  "form_1034": "Purifié",
  "form_1035": "Normal",
  "form_1036": "Obscur",
  "form_1037": "Purifié",
  "form_1038": "Normal",
  "form_1039": "Obscur",
  "form_1040": "Purifié",
  "form_1041": "Normal",
  "form_1042": "Obscur",
  "form_1043": "Purifié",
  "form_1044": "Normal",
  "form_1045": "Obscur",
  "form_1046": "Purifié",
  "form_1047": "Normal",
  "form_1048": "Obscur",
  "form_1049": "Purifié",
  "form_1050": "Normal",
  "form_1051": "Obscur",
  "form_1052": "Purifié",
  "form_1053": "Normal",
  "form_1054": "Obscur",
  "form_1055": "Purifié",
  "form_1056": "Normal",
  "form_1057": "Obscur",
  "form_1058": "Purifié",
  "form_1059": "Normal",
  "form_1060": "Obscur",
  "form_1061": "Purifié",
  "form_1062": "Normal",
  "form_1063": "Obscur",
  "form_1064": "Purifié",
  "form_1065": "Normal",
  "form_1066": "Obscur",
  "form_1067": "Purifié",
  "form_1068": "Normal",
  "form_1069": "Obscur",
  "form_1070": "Purifié",
  "form_1071": "Normal",
  "form_1072": "Obscur",
  "form_1073": "Purifié",
  "form_1074": "Normal",
  "form_1075": "Obscur",
  "form_1076": "Purifié",
  "form_1077": "Normal",
  "form_1078": "Obscur",
  "form_1079": "Purifié",
  "form_1080": "Normal",
  "form_1081": "Obscur",
  "form_1082": "Purifié",
  "form_1083": "Normal",
  "form_1084": "Obscur",
  "form_1085": "Purifié",
  "form_1086": "Normal",
  "form_1087": "Obscur",
  "form_1088": "Purifié",
  "form_1089": "Normal",
  "form_1090": "Obscur",
  "form_1091": "Purifié",
  "form_1092": "Normal",
  "form_1093": "Obscur",
  "form_1094": "Purifié",
  "form_1095": "Normal",
  "form_1096": "Obscur",
  "form_1097": "Purifié",
  "form_1098": "Normal",
  "form_1099": "Obscur",
  "form_1100": "Purifié",
  "form_1101": "Normal",
  "form_1102": "Obscur",
  "form_1103": "Purifié",
  "form_1104": "Normal",
  "form_1105": "Obscur",
  "form_1106": "Purifié",
  "form_1107": "Normal",
  "form_1108": "Obscur",
  "form_1109": "Purifié",
  "form_1110": "Normal",
  "form_1111": "Obscur",
  "form_1112": "Purifié",
  "form_1113": "Obscur",
  "form_1114": "Purifié",
  "form_1115": "Normal",
  "form_1116": "Obscur",
  "form_1117": "Purifié",
  "form_1118": "Normal",
  "form_1119": "Obscur",
  "form_1120": "Purifié",
  "form_1121": "Normal",
  "form_1122": "Obscur",
  "form_1123": "Purifié",
  "form_1124": "Normal",
  "form_1125": "Obscur",
  "form_1126": "Purifié",
  "form_1127": "Normal",
  "form_1128": "Obscur",
  "form_1129": "Purifié",
  "form_1130": "Normal",
  "form_1131": "Obscur",
  "form_1132": "Purifié",
  "form_1133": "Normal",
  "form_1134": "Obscur",
  "form_1135": "Purifié",
  "form_1136": "Normal",
  "form_1137": "Obscur",
  "form_1138": "Purifié",
  "form_1139": "Normal",
  "form_1140": "Obscur",
  "form_1141": "Purifié",
  "form_1142": "Normal",
  "form_1143": "Obscur",
  "form_1144": "Purifié",
  "form_1145": "Normal",
  "form_1146": "Obscur",
  "form_1147": "Purifié",
  "form_1148": "Normal",
  "form_1149": "Obscur",
  "form_1150": "Purifié",
  "form_1151": "Normal",
  "form_1152": "Obscur",
  "form_1153": "Purifié",
  "form_1154": "Normal",
  "form_1155": "Obscur",
  "form_1156": "Purifié",
  "form_1157": "Normal",
  "form_1158": "Obscur",
  "form_1159": "Purifié",
  "form_1160": "Normal",
  "form_1161": "Obscur",
  "form_1162": "Purifié",
  "form_1163": "Normal",
  "form_1164": "Obscur",
  "form_1165": "Purifié",
  "form_1166": "Normal",
  "form_1167": "Obscur",
  "form_1168": "Purifié",
  "form_1169": "Normal",
  "form_1170": "Obscur",
  "form_1171": "Purifié",
  "form_1172": "Normal",
  "form_1173": "Obscur",
  "form_1174": "Purifié",
  "form_1175": "Normal",
  "form_1176": "Obscur",
  "form_1177": "Purifié",
  "form_1178": "Normal",
  "form_1179": "Obscur",
  "form_1180": "Purifié",
  "form_1181": "Normal",
  "form_1182": "Obscur",
  "form_1183": "Purifié",
  "form_1184": "Normal",
  "form_1185": "Obscur",
  "form_1186": "Purifié",
  "form_1187": "Normal",
  "form_1188": "Obscur",
  "form_1189": "Purifié",
  "form_1190": "Normal",
  "form_1191": "Obscur",
  "form_1192": "Purifié",
  "form_1193": "Normal",
  "form_1194": "Obscur",
  "form_1195": "Purifié",
  "form_1196": "Normal",
  "form_1197": "Obscur",
  "form_1198": "Purifié",
  "form_1199": "Normal",
  "form_1200": "Obscur",
  "form_1201": "Purifié",
  "form_1202": "Normal",
  "form_1203": "Obscur",
  "form_1204": "Purifié",
  "form_1205": "Normal",
  "form_1206": "Obscur",
  "form_1207": "Purifié",
  "form_1208": "Normal",
  "form_1209": "Obscur",
  "form_1210": "Purifié",
  "form_1211": "Normal",
  "form_1212": "Obscur",
  "form_1213": "Purifié",
  "form_1214": "Normal",
  "form_1215": "Obscur",
  "form_1216": "Purifié",
  "form_1217": "Normal",
  "form_1218": "Obscur",
  "form_1219": "Purifié",
  "form_1220": "Normal",
  "form_1221": "Obscur",
  "form_1222": "Purifié",
  "form_1223": "Normal",
  "form_1224": "Obscur",
  "form_1225": "Purifié",
  "form_1226": "Normal",
  "form_1227": "Obscur",
  "form_1228": "Purifié",
  "form_1229": "Normal",
  "form_1230": "Obscur",
  "form_1231": "Purifié",
  "form_1232": "Normal",
  "form_1233": "Obscur",
  "form_1234": "Purifié",
  "form_1235": "Normal",
  "form_1236": "Obscur",
  "form_1237": "Purifié",
  "form_1238": "Normal",
  "form_1239": "Obscur",
  "form_1240": "Purifié",
  "form_1241": "Normal",
  "form_1242": "Obscur",
  "form_1243": "Purifié",
  "form_1244": "Normal",
  "form_1245": "Obscur",
  "form_1246": "Purifié",
  "form_1247": "Normal",
  "form_1248": "Obscur",
  "form_1249": "Purifié",
  "form_1250": "Normal",
  "form_1251": "Obscur",
  "form_1252": "Purifié",
  "form_1253": "Normal",
  "form_1254": "Obscur",
  "form_1255": "Purifié",
  "form_1256": "Normal",
  "form_1257": "Obscur",
  "form_1258": "Purifié",
  "form_1259": "Normal",
  "form_1260": "Obscur",
  "form_1261": "Purifié",
  "form_1262": "Normal",
  "form_1263": "Obscur",
  "form_1264": "Purifié",
  "form_1265": "Normal",
  "form_1266": "Obscur",
  "form_1267": "Purifié",
  "form_1268": "Normal",
  "form_1269": "Obscur",
  "form_1270": "Purifié",
  "form_1271": "Normal",
  "form_1272": "Obscur",
  "form_1273": "Purifié",
  "form_1274": "Normal",
  "form_1275": "Obscur",
  "form_1276": "Purifié",
  "form_1277": "Normal",
  "form_1278": "Obscur",
  "form_1279": "Purifié",
  "form_1280": "Normal",
  "form_1281": "Obscur",
  "form_1282": "Purifié",
  "form_1283": "Normal",
  "form_1284": "Obscur",
  "form_1285": "Purifié",
  "form_1286": "Normal",
  "form_1287": "Obscur",
  "form_1288": "Purifié",
  "form_1289": "Normal",
  "form_1290": "Obscur",
  "form_1291": "Purifié",
  "form_1292": "Normal",
  "form_1293": "Obscur",
  "form_1294": "Purifié",
  "form_1295": "Normal",
  "form_1296": "Obscur",
  "form_1297": "Purifié",
  "form_1298": "Normal",
  "form_1299": "Obscur",
  "form_1300": "Purifié",
  "form_1301": "Normal",
  "form_1302": "Obscur",
  "form_1303": "Purifié",
  "form_1304": "Normal",
  "form_1305": "Obscur",
  "form_1306": "Purifié",
  "form_1307": "Normal",
  "form_1308": "Obscur",
  "form_1309": "Purifié",
  "form_1310": "Normal",
  "form_1311": "Obscur",
  "form_1312": "Purifié",
  "form_1313": "Normal",
  "form_1314": "Obscur",
  "form_1315": "Purifié",
  "form_1316": "Normal",
  "form_1317": "Obscur",
  "form_1318": "Purifié",
  "form_1319": "Normal",
  "form_1320": "Obscur",
  "form_1321": "Purifié",
  "form_1322": "Normal",
  "form_1323": "Obscur",
  "form_1324": "Purifié",
  "form_1325": "Normal",
  "form_1326": "Obscur",
  "form_1327": "Purifié",
  "form_1328": "Normal",
  "form_1329": "Obscur",
  "form_1330": "Purifié",
  "form_1331": "Normal",
  "form_1332": "Obscur",
  "form_1333": "Purifié",
  "form_1334": "Normal",
  "form_1335": "Obscur",
  "form_1336": "Purifié",
  "form_1337": "Normal",
  "form_1338": "Obscur",
  "form_1339": "Purifié",
  "form_1340": "Normal",
  "form_1341": "Obscur",
  "form_1342": "Purifié",
  "form_1343": "Normal",
  "form_1344": "Obscur",
  "form_1345": "Purifié",
  "form_1346": "Normal",
  "form_1347": "Obscur",
  "form_1348": "Purifié",
  "form_1349": "Normal",
  "form_1350": "Obscur",
  "form_1351": "Purifié",
  "form_1352": "Normal",
  "form_1353": "Obscur",
  "form_1354": "Purifié",
  "form_1355": "Normal",
  "form_1356": "Obscur",
  "form_1357": "Purifié",
  "form_1358": "Normal",
  "form_1359": "Obscur",
  "form_1360": "Purifié",
  "form_1361": "Normal",
  "form_1362": "Obscur",
  "form_1363": "Purifié",
  "form_1364": "Normal",
  "form_1365": "Obscur",
  "form_1366": "Purifié",
  "form_1367": "Normal",
  "form_1368": "Obscur",
  "form_1369": "Purifié",
  "form_1370": "Normal",
  "form_1371": "Obscur",
  "form_1372": "Purifié",
  "form_1373": "Obscur",
  "form_1374": "Purifié",
  "form_1375": "Obscur",
  "form_1376": "Purifié",
  "form_1377": "Obscur",
  "form_1378": "Purifié",
  "form_1379": "Normal",
  "form_1380": "Obscur",
  "form_1381": "Purifié",
  "form_1382": "Normal",
  "form_1383": "Obscur",
  "form_1384": "Purifié",
  "form_1385": "Normal",
  "form_1386": "Obscur",
  "form_1387": "Purifié",
  "form_1388": "Normal",
  "form_1389": "Obscur",
  "form_1390": "Purifié",
  "form_1391": "Normal",
  "form_1392": "Obscur",
  "form_1393": "Purifié",
  "form_1394": "Normal",
  "form_1395": "Obscur",
  "form_1396": "Purifié",
  "form_1397": "Normal",
  "form_1398": "Obscur",
  "form_1399": "Purifié",
  "form_1400": "Normal",
  "form_1401": "Obscur",
  "form_1402": "Purifié",
  "form_1403": "Normal",
  "form_1404": "Obscur",
  "form_1405": "Purifié",
  "form_1406": "Normal",
  "form_1407": "Obscur",
  "form_1408": "Purifié",
  "form_1409": "Normal",
  "form_1410": "Obscur",
  "form_1411": "Purifié",
  "form_1412": "Normal",
  "form_1413": "Obscur",
  "form_1414": "Purifié",
  "form_1415": "Normal",
  "form_1416": "Obscur",
  "form_1417": "Purifié",
  "form_1418": "Normal",
  "form_1419": "Obscur",
  "form_1420": "Purifié",
  "form_1421": "Normal",
  "form_1422": "Obscur",
  "form_1423": "Purifié",
  "form_1424": "Normal",
  "form_1425": "Obscur",
  "form_1426": "Purifié",
  "form_1427": "Normal",
  "form_1428": "Obscur",
  "form_1429": "Purifié",
  "form_1430": "Normal",
  "form_1431": "Obscur",
  "form_1432": "Purifié",
  "form_1433": "Normal",
  "form_1434": "Obscur",
  "form_1435": "Purifié",
  "form_1436": "Normal",
  "form_1437": "Obscur",
  "form_1438": "Purifié",
  "form_1439": "Normal",
  "form_1440": "Obscur",
  "form_1441": "Purifié",
  "form_1442": "Normal",
  "form_1443": "Obscur",
  "form_1444": "Purifié",
  "form_1445": "Normal",
  "form_1446": "Obscur",
  "form_1447": "Purifié",
  "form_1448": "Normal",
  "form_1449": "Obscur",
  "form_1450": "Purifié",
  "form_1451": "Normal",
  "form_1452": "Obscur",
  "form_1453": "Purifié",
  "form_1454": "Normal",
  "form_1455": "Obscur",
  "form_1456": "Purifié",
  "form_1457": "Normal",
  "form_1458": "Obscur",
  "form_1459": "Purifié",
  "form_1460": "Normal",
  "form_1461": "Obscur",
  "form_1462": "Purifié",
  "form_1463": "Normal",
  "form_1464": "Obscur",
  "form_1465": "Purifié",
  "form_1466": "Normal",
  "form_1467": "Obscur",
  "form_1468": "Purifié",
  "form_1469": "Normal",
  "form_1470": "Obscur",
  "form_1471": "Purifié",
  "form_1472": "Normal",
  "form_1473": "Obscur",
  "form_1474": "Purifié",
  "form_1475": "Normal",
  "form_1476": "Obscur",
  "form_1477": "Purifié",
  "form_1478": "Normal",
  "form_1479": "Obscur",
  "form_1480": "Purifié",
  "form_1481": "Normal",
  "form_1482": "Obscur",
  "form_1483": "Purifié",
  "form_1484": "Normal",
  "form_1485": "Obscur",
  "form_1486": "Purifié",
  "form_1487": "Normal",
  "form_1488": "Obscur",
  "form_1489": "Purifié",
  "form_1490": "Normal",
  "form_1491": "Obscur",
  "form_1492": "Purifié",
  "form_1493": "Normal",
  "form_1494": "Obscur",
  "form_1495": "Purifié",
  "form_1496": "Normal",
  "form_1497": "Obscur",
  "form_1498": "Purifié",
  "form_1499": "Normal",
  "form_1500": "Obscur",
  "form_1501": "Purifié",
  "form_1502": "Normal",
  "form_1503": "Obscur",
  "form_1504": "Purifié",
  "form_1505": "Normal",
  "form_1506": "Obscur",
  "form_1507": "Purifié",
  "form_1508": "Normal",
  "form_1509": "Obscur",
  "form_1510": "Purifié",
  "form_1511": "Normal",
  "form_1512": "Obscur",
  "form_1513": "Purifié",
  "form_1514": "Normal",
  "form_1515": "Obscur",
  "form_1516": "Purifié",
  "form_1517": "Normal",
  "form_1518": "Obscur",
  "form_1519": "Purifié",
  "form_1520": "Normal",
  "form_1521": "Obscur",
  "form_1522": "Purifié",
  "form_1523": "Normal",
  "form_1524": "Obscur",
  "form_1525": "Purifié",
  "form_1526": "Normal",
  "form_1527": "Obscur",
  "form_1528": "Purifié",
  "form_1529": "Normal",
  "form_1530": "Obscur",
  "form_1531": "Purifié",
  "form_1532": "Normal",
  "form_1533": "Obscur",
  "form_1534": "Purifié",
  "form_1535": "Normal",
  "form_1536": "Obscur",
  "form_1537": "Purifié",
  "form_1538": "Normal",
  "form_1539": "Obscur",
  "form_1540": "Purifié",
  "form_1541": "Normal",
  "form_1542": "Obscur",
  "form_1543": "Purifié",
  "form_1544": "Normal",
  "form_1545": "Obscur",
  "form_1546": "Purifié",
  "form_1547": "Normal",
  "form_1548": "Obscur",
  "form_1549": "Purifié",
  "form_1550": "Normal",
  "form_1551": "Obscur",
  "form_1552": "Purifié",
  "form_1553": "Normal",
  "form_1554": "Obscur",
  "form_1555": "Purifié",
  "form_1556": "Normal",
  "form_1557": "Obscur",
  "form_1558": "Purifié",
  "form_1559": "Normal",
  "form_1560": "Obscur",
  "form_1561": "Purifié",
  "form_1562": "Normal",
  "form_1563": "Obscur",
  "form_1564": "Purifié",
  "form_1565": "Normal",
  "form_1566": "Obscur",
  "form_1567": "Purifié",
  "form_1568": "Normal",
  "form_1569": "Obscur",
  "form_1570": "Purifié",
  "form_1571": "Normal",
  "form_1572": "Obscur",
  "form_1573": "Purifié",
  "form_1574": "Normal",
  "form_1575": "Obscur",
  "form_1576": "Purifié",
  "form_1577": "Normal",
  "form_1578": "Obscur",
  "form_1579": "Purifié",
  "form_1580": "Normal",
  "form_1581": "Obscur",
  "form_1582": "Purifié",
  "form_1583": "Normal",
  "form_1584": "Obscur",
  "form_1585": "Purifié",
  "form_1586": "Normal",
  "form_1587": "Obscur",
  "form_1588": "Purifié",
  "form_1589": "Normal",
  "form_1590": "Obscur",
  "form_1591": "Purifié",
  "form_1592": "Normal",
  "form_1593": "Obscur",
  "form_1594": "Purifié",
  "form_1595": "Normal",
  "form_1596": "Obscur",
  "form_1597": "Purifié",
  "form_1598": "Normal",
  "form_1599": "Obscur",
  "form_1600": "Purifié",
  "form_1601": "Normal",
  "form_1602": "Obscur",
  "form_1603": "Purifié",
  "form_1604": "Normal",
  "form_1605": "Obscur",
  "form_1606": "Purifié",
  "form_1607": "Normal",
  "form_1608": "Obscur",
  "form_1609": "Purifié",
  "form_1610": "Normal",
  "form_1611": "Obscur",
  "form_1612": "Purifié",
  "form_1613": "Normal",
  "form_1614": "Obscur",
  "form_1615": "Purifié",
  "form_1616": "Normal",
  "form_1617": "Obscur",
  "form_1618": "Purifié",
  "form_1619": "Normal",
  "form_1620": "Obscur",
  "form_1621": "Purifié",
  "form_1622": "Normal",
  "form_1623": "Obscur",
  "form_1624": "Purifié",
  "form_1625": "Normal",
  "form_1626": "Obscur",
  "form_1627": "Purifié",
  "form_1628": "Normal",
  "form_1629": "Obscur",
  "form_1630": "Purifié",
  "form_1631": "Normal",
  "form_1632": "Obscur",
  "form_1633": "Purifié",
  "form_1634": "Normal",
  "form_1635": "Obscur",
  "form_1636": "Purifié",
  "form_1637": "Normal",
  "form_1638": "Obscur",
  "form_1639": "Purifié",
  "form_1640": "Normal",
  "form_1641": "Obscur",
  "form_1642": "Purifié",
  "form_1643": "Normal",
  "form_1644": "Obscur",
  "form_1645": "Purifié",
  "form_1646": "Normal",
  "form_1647": "Obscur",
  "form_1648": "Purifié",
  "form_1649": "Normal",
  "form_1650": "Obscur",
  "form_1651": "Purifié",
  "form_1652": "Normal",
  "form_1653": "Obscur",
  "form_1654": "Purifié",
  "form_1655": "Normal",
  "form_1656": "Obscur",
  "form_1657": "Purifié",
  "form_1658": "Normal",
  "form_1659": "Obscur",
  "form_1660": "Purifié",
  "form_1661": "Normal",
  "form_1662": "Obscur",
  "form_1663": "Purifié",
  "form_1664": "Normal",
  "form_1665": "Obscur",
  "form_1666": "Purifié",
  "form_1667": "Normal",
  "form_1668": "Obscur",
  "form_1669": "Purifié",
  "form_1670": "Normal",
  "form_1671": "Obscur",
  "form_1672": "Purifié",
  "form_1673": "Normal",
  "form_1674": "Obscur",
  "form_1675": "Purifié",
  "form_1676": "Normal",
  "form_1677": "Obscur",
  "form_1678": "Purifié",
  "form_1679": "Normal",
  "form_1680": "Obscur",
  "form_1681": "Purifié",
  "form_1682": "Normal",
  "form_1683": "Obscur",
  "form_1684": "Purifié",
  "form_1685": "Normal",
  "form_1686": "Obscur",
  "form_1687": "Purifié",
  "form_1688": "Normal",
  "form_1689": "Obscur",
  "form_1690": "Purifié",
  "form_1691": "Normal",
  "form_1692": "Obscur",
  "form_1693": "Purifié",
  "form_1694": "Normal",
  "form_1695": "Obscur",
  "form_1696": "Purifié",
  "form_1697": "Normal",
  "form_1698": "Obscur",
  "form_1699": "Purifié",
  "form_1700": "Normal",
  "form_1701": "Obscur",
  "form_1702": "Purifié",
  "form_1703": "Normal",
  "form_1704": "Obscur",
  "form_1705": "Purifié",
  "form_1706": "Normal",
  "form_1707": "Obscur",
  "form_1708": "Purifié",
  "form_1709": "Normal",
  "form_1710": "Obscur",
  "form_1711": "Purifié",
  "form_1712": "Normal",
  "form_1713": "Obscur",
  "form_1714": "Purifié",
  "form_1715": "Normal",
  "form_1716": "Obscur",
  "form_1717": "Purifié",
  "form_1718": "Normal",
  "form_1719": "Obscur",
  "form_1720": "Purifié",
  "form_1721": "Normal",
  "form_1722": "Obscur",
  "form_1723": "Purifié",
  "form_1724": "Normal",
  "form_1725": "Obscur",
  "form_1726": "Purifié",
  "form_1727": "Normal",
  "form_1728": "Obscur",
  "form_1729": "Purifié",
  "form_1730": "Normal",
  "form_1731": "Obscur",
  "form_1732": "Purifié",
  "form_1733": "Normal",
  "form_1734": "Obscur",
  "form_1735": "Purifié",
  "form_1736": "Normal",
  "form_1737": "Obscur",
  "form_1738": "Purifié",
  "form_1739": "Normal",
  "form_1740": "Obscur",
  "form_1741": "Purifié",
  "form_1742": "Normal",
  "form_1743": "Obscur",
  "form_1744": "Purifié",
  "form_1745": "Normal",
  "form_1746": "Obscur",
  "form_1747": "Purifié",
  "form_1748": "Normal",
  "form_1749": "Obscur",
  "form_1750": "Purifié",
  "form_1751": "Normal",
  "form_1752": "Obscur",
  "form_1753": "Purifié",
  "form_1754": "Normal",
  "form_1755": "Obscur",
  "form_1756": "Purifié",
  "form_1757": "Normal",
  "form_1758": "Obscur",
  "form_1759": "Purifié",
  "form_1760": "Normal",
  "form_1761": "Obscur",
  "form_1762": "Purifié",
  "form_1763": "Normal",
  "form_1764": "Obscur",
  "form_1765": "Purifié",
  "form_1766": "Normal",
  "form_1767": "Obscur",
  "form_1768": "Purifié",
  "form_1769": "Normal",
  "form_1770": "Obscur",
  "form_1771": "Purifié",
  "form_1772": "Normal",
  "form_1773": "Obscur",
  "form_1774": "Purifié",
  "form_1775": "Normal",
  "form_1776": "Obscur",
  "form_1777": "Purifié",
  "form_1778": "Normal",
  "form_1779": "Obscur",
  "form_1780": "Purifié",
  "form_1781": "Normal",
  "form_1782": "Obscur",
  "form_1783": "Purifié",
  "form_1784": "Normal",
  "form_1785": "Obscur",
  "form_1786": "Purifié",
  "form_1787": "Normal",
  "form_1788": "Obscur",
  "form_1789": "Purifié",
  "form_1790": "Normal",
  "form_1791": "Obscur",
  "form_1792": "Purifié",
  "form_1793": "Normal",
  "form_1794": "Obscur",
  "form_1795": "Purifié",
  "form_1796": "Normal",
  "form_1797": "Obscur",
  "form_1798": "Purifié",
  "form_1799": "Normal",
  "form_1800": "Obscur",
  "form_1801": "Purifié",
  "form_1802": "Normal",
  "form_1803": "Obscur",
  "form_1804": "Purifié",
  "form_1805": "Normal",
  "form_1806": "Obscur",
  "form_1807": "Purifié",
  "form_1808": "Normal",
  "form_1809": "Obscur",
  "form_1810": "Purifié",
  "form_1811": "Normal",
  "form_1812": "Obscur",
  "form_1813": "Purifié",
  "form_1814": "Normal",
  "form_1815": "Obscur",
  "form_1816": "Purifié",
  "form_1817": "Normal",
  "form_1818": "Obscur",
  "form_1819": "Purifié",
  "form_1820": "Normal",
  "form_1821": "Obscur",
  "form_1822": "Purifié",
  "form_1823": "Normal",
  "form_1824": "Obscur",
  "form_1825": "Purifié",
  "form_1826": "Normal",
  "form_1827": "Obscur",
  "form_1828": "Purifié",
  "form_1829": "Normal",
  "form_1830": "Obscur",
  "form_1831": "Purifié",
  "form_1832": "Normal",
  "form_1833": "Obscur",
  "form_1834": "Purifié",
  "form_1835": "Normal",
  "form_1836": "Obscur",
  "form_1837": "Purifié",
  "form_1838": "Normal",
  "form_1839": "Obscur",
  "form_1840": "Purifié",
  "form_1841": "Normal",
  "form_1842": "Obscur",
  "form_1843": "Purifié",
  "form_1844": "Normal",
  "form_1845": "Obscur",
  "form_1846": "Purifié",
  "form_1847": "Normal",
  "form_1848": "Obscur",
  "form_1849": "Purifié",
  "form_1850": "Normal",
  "form_1851": "Obscur",
  "form_1852": "Purifié",
  "form_1853": "Normal",
  "form_1854": "Obscur",
  "form_1855": "Purifié",
  "form_1856": "Normal",
  "form_1857": "Obscur",
  "form_1858": "Purifié",
  "form_1859": "Normal",
  "form_1860": "Obscur",
  "form_1861": "Purifié",
  "form_1862": "Normal",
  "form_1863": "Obscur",
  "form_1864": "Purifié",
  "form_1865": "Normal",
  "form_1866": "Obscur",
  "form_1867": "Purifié",
  "form_1868": "Normal",
  "form_1869": "Obscur",
  "form_1870": "Purifié",
  "form_1871": "Normal",
  "form_1872": "Obscur",
  "form_1873": "Purifié",
  "form_1874": "Normal",
  "form_1875": "Obscur",
  "form_1876": "Purifié",
  "form_1877": "Normal",
  "form_1878": "Obscur",
  "form_1879": "Purifié",
  "form_1880": "Normal",
  "form_1881": "Obscur",
  "form_1882": "Purifié",
  "form_1883": "Normal",
  "form_1884": "Obscur",
  "form_1885": "Purifié",
  "form_1886": "Normal",
  "form_1887": "Obscur",
  "form_1888": "Purifié",
  "form_1889": "Normal",
  "form_1890": "Obscur",
  "form_1891": "Purifié",
  "form_1892": "Normal",
  "form_1893": "Obscur",
  "form_1894": "Purifié",
  "form_1895": "Normal",
  "form_1896": "Obscur",
  "form_1897": "Purifié",
  "form_1898": "Normal",
  "form_1899": "Obscur",
  "form_1900": "Purifié",
  "form_1901": "Normal",
  "form_1902": "Obscur",
  "form_1903": "Purifié",
  "form_1904": "Normal",
  "form_1905": "Obscur",
  "form_1906": "Purifié",
  "form_1907": "Normal",
  "form_1908": "Obscur",
  "form_1909": "Purifié",
  "form_1910": "Normal",
  "form_1911": "Obscur",
  "form_1912": "Purifié",
  "form_1913": "Normal",
  "form_1914": "Obscur",
  "form_1915": "Purifié",
  "form_1916": "Normal",
  "form_1917": "Obscur",
  "form_1918": "Purifié",
  "form_1919": "Normal",
  "form_1920": "Obscur",
  "form_1921": "Purifié",
  "form_1922": "Normal",
  "form_1923": "Obscur",
  "form_1924": "Purifié",
  "form_1925": "Normal",
  "form_1926": "Obscur",
  "form_1927": "Purifié",
  "form_1928": "Normal",
  "form_1929": "Obscur",
  "form_1930": "Purifié",
  "form_1931": "Normal",
  "form_1932": "Obscur",
  "form_1933": "Purifié",
  "form_1934": "Normal",
  "form_1935": "Obscur",
  "form_1936": "Purifié",
  "form_1937": "Normal",
  "form_1938": "Obscur",
  "form_1939": "Purifié",
  "form_1940": "Normal",
  "form_1941": "Obscur",
  "form_1942": "Purifié",
  "form_1943": "Normal",
  "form_1944": "Obscur",
  "form_1945": "Purifié",
  "form_1946": "Normal",
  "form_1947": "Obscur",
  "form_1948": "Purifié",
  "form_1949": "Normal",
  "form_1950": "Obscur",
  "form_1951": "Purifié",
  "form_1952": "Normal",
  "form_1953": "Obscur",
  "form_1954": "Purifié",
  "form_1955": "Normal",
  "form_1956": "Obscur",
  "form_1957": "Purifié",
  "form_1958": "Normal",
  "form_1959": "Obscur",
  "form_1960": "Purifié",
  "form_1961": "Normal",
  "form_1962": "Obscur",
  "form_1963": "Purifié",
  "form_1964": "Normal",
  "form_1965": "Obscur",
  "form_1966": "Purifié",
  "form_1967": "Normal",
  "form_1968": "Obscur",
  "form_1969": "Purifié",
  "form_1970": "Normal",
  "form_1971": "Obscur",
  "form_1972": "Purifié",
  "form_1973": "Normal",
  "form_1974": "Obscur",
  "form_1975": "Purifié",
  "form_1976": "Normal",
  "form_1977": "Obscur",
  "form_1978": "Purifié",
  "form_1979": "Normal",
  "form_1980": "Obscur",
  "form_1981": "Purifié",
  "form_1982": "Normal",
  "form_1983": "Obscur",
  "form_1984": "Purifié",
  "form_1985": "Normal",
  "form_1986": "Obscur",
  "form_1987": "Purifié",
  "form_1988": "Normal",
  "form_1989": "Obscur",
  "form_1990": "Purifié",
  "form_1991": "Normal",
  "form_1992": "Obscur",
  "form_1993": "Purifié",
  "form_1994": "Normal",
  "form_1995": "Obscur",
  "form_1996": "Purifié",
  "form_1997": "Normal",
  "form_1998": "Obscur",
  "form_1999": "Purifié",
  "form_2000": "Normal",
  "form_2001": "Obscur",
  "form_2002": "Purifié",
  "form_2003": "Normal",
  "form_2004": "Obscur",
  "form_2005": "Purifié",
  "form_2006": "Normal",
  "form_2007": "Obscur",
  "form_2008": "Purifié",
  "form_2009": "Normal",
  "form_2010": "Obscur",
  "form_2011": "Purifié",
  "form_2012": "Normal",
  "form_2013": "Obscur",
  "form_2014": "Purifié",
  "form_2015": "Normal",
  "form_2016": "Obscur",
  "form_2017": "Purifié",
  "form_2018": "Normal",
  "form_2019": "Obscur",
  "form_2020": "Purifié",
  "form_2021": "Normal",
  "form_2022": "Obscur",
  "form_2023": "Purifié",
  "form_2024": "Normal",
  "form_2025": "Obscur",
  "form_2026": "Purifié",
  "form_2027": "Normal",
  "form_2028": "Obscur",
  "form_2029": "Purifié",
  "form_2030": "Normal",
  "form_2031": "Obscur",
  "form_2032": "Purifié",
  "form_2033": "Normal",
  "form_2034": "Obscur",
  "form_2035": "Purifié",
  "form_2036": "Normal",
  "form_2037": "Obscur",
  "form_2038": "Purifié",
  "form_2039": "Normal",
  "form_2040": "Obscur",
  "form_2041": "Purifié",
  "form_2042": "Normal",
  "form_2043": "Obscur",
  "form_2044": "Purifié",
  "form_2045": "Normal",
  "form_2046": "Obscur",
  "form_2047": "Purifié",
  "form_2048": "Normal",
  "form_2049": "Obscur",
  "form_2050": "Purifié",
  "form_2051": "Normal",
  "form_2052": "Obscur",
  "form_2053": "Purifié",
  "form_2054": "Normal",
  "form_2055": "Obscur",
  "form_2056": "Purifié",
  "form_2057": "Normal",
  "form_2058": "Obscur",
  "form_2059": "Purifié",
  "form_2060": "Normal",
  "form_2061": "Obscur",
  "form_2062": "Purifié",
  "form_2063": "Normal",
  "form_2064": "Obscur",
  "form_2065": "Purifié",
  "form_2066": "Normal",
  "form_2067": "Obscur",
  "form_2068": "Purifié",
  "form_2069": "Normal",
  "form_2070": "Obscur",
  "form_2071": "Purifié",
  "form_2072": "Normal",
  "form_2073": "Obscur",
  "form_2074": "Purifié",
  "form_2075": "Normal",
  "form_2076": "Obscur",
  "form_2077": "Purifié",
  "form_2078": "Normal",
  "form_2079": "Obscur",
  "form_2080": "Purifié",
  "form_2081": "Normal",
  "form_2082": "Obscur",
  "form_2083": "Purifié",
  "form_2084": "Normal",
  "form_2085": "Obscur",
  "form_2086": "Purifié",
  "form_2087": "Normal",
  "form_2088": "Obscur",
  "form_2089": "Purifié",
  "form_2090": "Normal",
  "form_2091": "Obscur",
  "form_2092": "Purifié",
  "form_2093": "Normal",
  "form_2094": "Obscur",
  "form_2095": "Purifié",
  "form_2096": "Normal",
  "form_2097": "Obscur",
  "form_2098": "Purifié",
  "form_2099": "Normal",
  "form_2100": "Obscur",
  "form_2101": "Purifié",
  "form_2102": "Normal",
  "form_2103": "Obscur",
  "form_2104": "Purifié",
  "form_2105": "Normal",
  "form_2106": "Obscur",
  "form_2107": "Purifié",
  "form_2108": "Normal",
  "form_2109": "Obscur",
  "form_2110": "Purifié",
  "form_2111": "Normal",
  "form_2112": "Obscur",
  "form_2113": "Purifié",
  "form_2114": "Normal",
  "form_2115": "Obscur",
  "form_2116": "Purifié",
  "form_2117": "Normal",
  "form_2118": "Obscur",
  "form_2119": "Purifié",
  "form_2120": "Normal",
  "form_2121": "Obscur",
  "form_2122": "Purifié",
  "form_2123": "Normal",
  "form_2124": "Obscur",
  "form_2125": "Purifié",
  "form_2126": "Normal",
  "form_2127": "Obscur",
  "form_2128": "Purifié",
  "form_2129": "Normal",
  "form_2130": "Obscur",
  "form_2131": "Purifié",
  "form_2132": "Normal",
  "form_2133": "Obscur",
  "form_2134": "Purifié",
  "form_2135": "Normal",
  "form_2136": "Obscur",
  "form_2137": "Purifié",
  "form_2138": "Normal",
  "form_2139": "Obscur",
  "form_2140": "Purifié",
  "form_2141": "Normal",
  "form_2142": "Obscur",
  "form_2143": "Purifié",
  "form_2144": "Normal",
  "form_2145": "Obscur",
  "form_2146": "Purifié",
  "form_2147": "Normal",
  "form_2148": "Obscur",
  "form_2149": "Purifié",
  "form_2150": "Normal",
  "form_2151": "Obscur",
  "form_2152": "Purifié",
  "form_2153": "Normal",
  "form_2154": "Obscur",
  "form_2155": "Purifié",
  "form_2156": "Normal",
  "form_2157": "Obscur",
  "form_2158": "Purifié",
  "form_2159": "Normal",
  "form_2160": "Obscur",
  "form_2161": "Purifié",
  "form_2162": "Normal",
  "form_2163": "Obscur",
  "form_2164": "Purifié",
  "form_2165": "Normal",
  "form_2166": "Obscur",
  "form_2167": "Purifié",
  "form_2168": "Normal",
  "form_2169": "Obscur",
  "form_2170": "Purifié",
  "form_2171": "Normal",
  "form_2172": "Obscur",
  "form_2173": "Purifié",
  "form_2174": "Normal",
  "form_2175": "Obscur",
  "form_2176": "Purifié",
  "form_2177": "Normal",
  "form_2178": "Obscur",
  "form_2179": "Purifié",
  "form_2180": "Normal",
  "form_2181": "Obscur",
  "form_2182": "Purifié",
  "form_2183": "Normal",
  "form_2184": "Obscur",
  "form_2185": "Purifié",
  "form_2186": "Normal",
  "form_2187": "Obscur",
  "form_2188": "Purifié",
  "form_2189": "Normal",
  "form_2190": "Obscur",
  "form_2191": "Purifié",
  "form_2192": "Normal",
  "form_2193": "Obscur",
  "form_2194": "Purifié",
  "form_2195": "Normal",
  "form_2196": "Obscur",
  "form_2197": "Purifié",
  "form_2198": "Normal",
  "form_2199": "Obscur",
  "form_2200": "Purifié",
  "form_2201": "Normal",
  "form_2202": "Obscur",
  "form_2203": "Purifié",
  "form_2204": "Normal",
  "form_2205": "Obscur",
  "form_2206": "Purifié",
  "form_2207": "Normal",
  "form_2208": "Obscur",
  "form_2209": "Purifié",
  "form_2210": "Normal",
  "form_2211": "Obscur",
  "form_2212": "Purifié",
  "form_2213": "Normal",
  "form_2214": "Obscur",
  "form_2215": "Purifié",
  "form_2216": "Normal",
  "form_2217": "Obscur",
  "form_2218": "Purifié",
  "form_2219": "Normal",
  "form_2220": "Obscur",
  "form_2221": "Purifié",
  "form_2222": "Normal",
  "form_2223": "Obscur",
  "form_2224": "Purifié",
  "form_2225": "Normal",
  "form_2226": "Obscur",
  "form_2227": "Purifié",
  "form_2228": "Normal",
  "form_2229": "Obscur",
  "form_2230": "Purifié",
  "form_2231": "Normal",
  "form_2232": "Obscur",
  "form_2233": "Purifié",
  "form_2234": "Normal",
  "form_2235": "Obscur",
  "form_2236": "Purifié",
  "form_2237": "Normal",
  "form_2238": "Obscur",
  "form_2239": "Purifié",
  "form_2240": "Normal",
  "form_2241": "Obscur",
  "form_2242": "Purifié",
  "form_2243": "Normal",
  "form_2244": "Obscur",
  "form_2245": "Purifié",
  "form_2246": "Normal",
  "form_2247": "Obscur",
  "form_2248": "Purifié",
  "form_2249": "Normal",
  "form_2250": "Obscur",
  "form_2251": "Purifié",
  "form_2252": "Normal",
  "form_2253": "Obscur",
  "form_2254": "Purifié",
  "form_2255": "Normal",
  "form_2256": "Obscur",
  "form_2257": "Purifié",
  "form_2258": "Normal",
  "form_2259": "Obscur",
  "form_2260": "Purifié",
  "form_2261": "Normal",
  "form_2262": "Obscur",
  "form_2263": "Purifié",
  "form_2264": "Normal",
  "form_2265": "Obscur",
  "form_2266": "Purifié",
  "form_2267": "Normal",
  "form_2268": "Obscur",
  "form_2269": "Purifié",
  "form_2270": "Normal",
  "form_2271": "Obscur",
  "form_2272": "Purifié",
  "form_2273": "Normal",
  "form_2274": "Obscur",
  "form_2275": "Purifié",
  "form_2276": "Normal",
  "form_2277": "Obscur",
  "form_2278": "Purifié",
  "form_2279": "Normal",
  "form_2280": "Obscur",
  "form_2281": "Purifié",
  "form_2282": "Normal",
  "form_2283": "Obscur",
  "form_2284": "Purifié",
  "form_2285": "Normal",
  "form_2286": "Obscur",
  "form_2287": "Purifié",
  "form_2288": "Normal",
  "form_2289": "Obscur",
  "form_2290": "Purifié",
  "form_2291": "Normal",
  "form_2292": "Obscur",
  "form_2293": "Purifié",
  "form_2294": "Normal",
  "form_2295": "Obscur",
  "form_2296": "Purifié",
  "form_2297": "Normal",
  "form_2298": "Obscur",
  "form_2299": "Purifié",
  "form_2300": "Normal",
  "form_2301": "Obscur",
  "form_2302": "Purifié",
  "form_2303": "Normal",
  "form_2304": "Obscur",
  "form_2305": "Purifié",
  "form_2306": "Normal",
  "form_2307": "Obscur",
  "form_2308": "Purifié",
  "form_2309": "Normal",
  "form_2310": "Obscur",
  "form_2311": "Purifié",
  "form_2312": "Normal",
  "form_2313": "Obscur",
  "form_2314": "Purifié",
  "form_2315": "Normal",
  "form_2316": "Obscur",
  "form_2317": "Purifié",
  "form_2318": "Normal",
  "form_2319": "Obscur",
  "form_2320": "Purifié",
  "form_2321": "Normal",
  "form_2322": "Obscur",
  "form_2323": "Purifié",
  "form_2324": "Normal",
  "form_2325": "Obscur",
  "form_2326": "Purifié",
  "form_2327": "Printemps 2020",
  "form_2328": "Printemps 2020",
  "form_2329": "Printemps 2020",
  "form_2330": "Femelle",
  "form_2331": "Femelle",
  "form_2332": "Costume 2020",
  "form_2333": "Costume 2020",
  "form_2334": "Costume 2020",
  "form_2335": "Galarian",
  "form_2336": "Galarian",
  "form_2337": "Galarian",
  "form_2338": "Galarian",
  "form_2339": "Galarian",
  "form_2340": "Galarian",
  "form_2341": "Galarian",
  "form_2342": "Galarian Standard",
  "form_2343": "Galarian Zen",
  "form_2344": "Galarian",
  "form_2345": "Galarian",
  "form_2501": "Normal",
  "form_2502": "Obscur",
  "form_2503": "Purifié",
  "form_2504": "Normal",
  "form_2505": "Obscur",
  "form_2506": "Purifié",
  "form_2510": "Normal",
  "form_2511": "Obscur",
  "form_2512": "Purifié",
  "form_2516": "Normal",
  "form_2517": "Obscur",
  "form_2518": "Purifié",
  "form_2582": "Galarian",
  "form_2583": "Galarian",
  "form_2584": "Galarian",
  "form_2585": "Costume 2020",
  "form_2586": "Costume 2020",
  "form_2587": "Normal",
  "form_2588": "Femelle",
  "form_2589": "Normal",
  "form_2590": "Femelle",
  "form_2591": "Ten Percent",
  "form_2592": "Fifty Percent",
  "form_2593": "Complete",
  "form_2594": "Archipelago",
  "form_2595": "Continental",
  "form_2596": "Elegant",
  "form_2597": "Fancy",
  "form_2598": "Garden",
  "form_2599": "High Plains",
  "form_2600": "Icy Snow",
  "form_2601": "Jungle",
  "form_2602": "Marine",
  "form_2603": "Meadow",
  "form_2604": "Modern",
  "form_2605": "Monsoon",
  "form_2606": "Ocean",
  "form_2607": "Pokeball",
  "form_2608": "Polar",
  "form_2609": "River",
  "form_2610": "Sandstorm",
  "form_2611": "Savanna",
  "form_2612": "Sun",
  "form_2613": "Tundra",
  "form_2614": "Red",
  "form_2615": "Yellow",
  "form_2616": "Orange",
  "form_2617": "Blue",
  "form_2618": "White",
  "form_2619": "Red",
  "form_2620": "Yellow",
  "form_2621": "Orange",
  "form_2622": "Blue",
  "form_2623": "White",
  "form_2624": "Red",
  "form_2625": "Yellow",
  "form_2626": "Orange",
  "form_2627": "Blue",
  "form_2628": "White",
  "form_2629": "Natural",
  "form_2630": "Heart",
  "form_2631": "Star",
  "form_2632": "Diamond",
  "form_2633": "Debutante",
  "form_2634": "Matron",
  "form_2635": "Dandy",
  "form_2636": "La Reine",
  "form_2637": "Kabuki",
  "form_2638": "Pharaoh",
  "form_2639": "Shield",
  "form_2640": "Blade",
  "form_2641": "Mini",
  "form_2642": "Normale",
  "form_2643": "Maxi",
  "form_2644": "Ultra",
  "form_2645": "Mini",
  "form_2646": "Normale",
  "form_2647": "Maxi",
  "form_2648": "Ultra",
  "form_2649": "Neutral",
  "form_2650": "Active",
  "form_2651": "Confined",
  "form_2652": "Unbound",
  "form_2666": "Costume 2020 Deprecated",
  "form_2668": "Costume 2020",
  "form_2669": "Adventure Hat 2020",
  "form_2670": "Hiver 2020",
  "form_2671": "Hiver 2020",
  "form_2672": "Hiver 2020",
  "form_2673": "2020",
  "form_2674": "2021",
  "costume_1": "Vacances",
  "costume_2": "Fête",
  "costume_3": "Ash",
  "costume_4": "Witch",
  "costume_5": "Aventure",
  "costume_6": "Casquette Noire",
  "costume_7": "Fleur",
  "costume_8": "Toque",
  "costume_9": "Détective",
  "costume_10": "One Piece",
  "costume_11": "Pokémon Day",
  "evo_1": "Méga",
  "evo_2": "Méga X",
  "evo_3": "Méga Y",
  "quest_0": "Type de Quête Inconnu",
  "quest_1": "%{amount} fois Première Capture du Jour",
  "quest_2": "%{amount} fois Premier Pokéstop du Jour",
  "quest_3": "Quête Multiple",
  "quest_4": "Attrape %{amount} Pokémon",
  "quest_5": "Fais tourner %{amount} Pokéstop(s)",
  "quest_6": "Fais éclore %{amount} Œuf(s)",
  "quest_7": "Combats %{amount} fois dans une Arène",
  "quest_8": "Combats %{amount} fois dans un Raid",
  "quest_9": "Termine %{amount} Quête(s)",
  "quest_10": "Transfère %{amount} Pokémon",
  "quest_11": "Ajoute %{amount} Pokémon à tes favoris",
  "quest_12": "Autocomplete",
  "quest_13": "Utilise %{amount} Baies pour t'aider à attraper des Pokémon",
  "quest_14": "Recharge %{amount} Pokémon",
  "quest_15": "Fais évoluer %{amount} Pokémon",
  "quest_16": "Fais %{amount} Lancer(s)",
  "quest_17": "Gagne %{amount} Bonbons en marchant avec ton Copain",
  "quest_18": "Gagne %{amount} Médaille(s)",
  "quest_19": "Gagne %{amount} Niveau",
  "quest_20": "Participe à %{amount} Combat(s) de Raid(s)",
  "quest_21": "Combats %{amount} fois",
  "quest_22": "Ajoute %{amount} Ami(s)",
  "quest_23": "Échange %{amount} Pokémon",
  "quest_24": "Envoie %{amount} Cadeau(x)",
  "quest_25": "Fais évoluer %{amount} Pokémon spécifique(s)",
  "quest_27": "Termine %{amount} Combat(s)",
  "quest_28": "Prends %{amount} Photo(s)",
  "quest_29": "Combats %{amount} fois la Team Rocket",
  "quest_30": "Purifie %{amount} Pokémon",
  "quest_31": "Trouve %{amount} Invasion(s) Team Rocket",
  "quest_32": "%{amount} fois Premier Sbire du Jour",
  "quest_33": "Donne %{amount} friandise(s) à ton Copain",
  "quest_34": "Gagne %{amount} coeurs avec ton Copain",
  "quest_35": "Joue %{amount} fois avec ton Copain",
  "quest_36": "Recharge ton Copain %{amount} fois",
  "quest_37": "Gagne %{amount} points d'Amitié en marchant avec ton Copain",
  "quest_38": "Gagne %{amount} Souvenirs de ton Copain",
  "quest_39": "Utilise un Encens %{amount} fois",
  "quest_40": "Obtiens %{amount} Souvenir(s) de ton Copain",
  "quest_41": "Obtiens %{amount} Récompenses",
  "quest_42": "Marche %{amount} km",
  "quest_43": "Fais Méga-évoluer %{amount} Pokémon",
  "quest_44": "Obtiens %{amount} Poussières Étoiles",
  "quest_46": "Cartographie RA",
  "quest_53": "Utilise %{amount} Attaque(s) Chargée(s)",
  "quest_55": "Combats %{amount} NPC(s) d'évènement",
  "quest_57": "Prends %{amount} Photo(s) de Pokémon sauvage(s)",
  "quest_58": "Utilise %{amount} Objet(s) de Pokémon",
  "quest_59": "Ouvre %{amount} Cadeau(x)",
  "quest_reward_0": "Indéfini",
  "quest_reward_1": "XP",
  "quest_reward_1_formatted": "%{amount} XP",
  "quest_reward_2": "Objet",
  "quest_reward_2_formatted": "%{amount} %{item}",
  "quest_reward_3": "Poussières Étoiles",
  "quest_reward_3_formatted": "%{amount} Poussières Étoiles",
  "quest_reward_4": "Bonbon",
  "quest_reward_4_formatted": "%{amount} %{Pokemon} Bonbon",
  "quest_reward_5": "Vêtement d'Avatar",
  "quest_reward_6": "Quête",
  "quest_reward_7": "Rencontre Pokémon",
  "quest_reward_7_formatted": "%{Pokemon}",
  "quest_reward_8": "PokéPièce",
  "quest_reward_8_formatted": "%{amount} PokéPièces",
  "quest_reward_11": "Autocollant",
  "quest_reward_12": "Méga-Énergie",
  "quest_reward_12_formatted": "%{amount} Méga-Énergie %{Pokemon}",
  "quest_condition_undefined": "",
  "quest_condition_0": "",
  "quest_condition_1": "Type de Pokémon",
  "quest_condition_1_formatted": "Type(s): %{types}",
  "quest_condition_2": "Catégorie de Pokémon",
  "quest_condition_2_formatted": "Pokémon: %{Pokemon}",
  "quest_condition_3": "Boosté par la Météo",
  "quest_condition_4": "Bonus de Capture du Jour",
  "quest_condition_5": "Bonus de Visite du Jour",
  "quest_condition_6": "Gagne le Raid",
  "quest_condition_7": "Raid Niveau",
  "quest_condition_7_formatted": "Raid Niveau(x): %{levels}",
  "quest_condition_8": "Type de lancer",
  "quest_condition_8_formatted": "%{throw_type} Lancer",
  "quest_condition_9": "Gagne le combat d'Arène",
  "quest_condition_10": "Attaque super efficace",
  "quest_condition_11": "Objet",
  "quest_condition_11_formatted": "Objet: %{item}",
  "quest_condition_12": "Pokéstop Unique",
  "quest_condition_13": "Contexte de la Quête",
  "quest_condition_14": "À la suite",
  "quest_condition_14_formatted": "%{throw_type} Lancer(s) à la suite",
  "quest_condition_15": "Lancer à effet",
  "quest_condition_16": "Type de Médaille",
  "quest_condition_17": "Niveau de Joueur",
  "quest_condition_18": "Gagne le Combat",
  "quest_condition_19": "Nouvel Ami",
  "quest_condition_20": "Jours à la suite",
  "quest_condition_21": "Pokémon Unique",
  "quest_condition_22": "Combat NPC",
  "quest_condition_23": "Combat PVP",
  "quest_condition_24": "Position",
  "quest_condition_25": "Distance",
  "quest_condition_26": "Forme de Pokémon",
  "quest_condition_26_formatted": "Forme(s) de Pokémon: %{alignments}",
  "quest_condition_27": "Catégorie d'Invasion",
  "quest_condition_27_formatted": "Catégorie(s) d'Invasion: %{categories}",
  "quest_condition_28": "Avec ton Copain",
  "quest_condition_31": "Niveau de Pokémon",
  "quest_condition_34": "PC Max",
  "quest_condition_35": "Pokémon chanceux",
  "quest_condition_36": "Pokémon Légendaire",
  "quest_condition_37": "Avec un Pokémon Méga évolué",
  "quest_condition_38": "Rang GBL",
  "quest_condition_39": "Captures à la suite",
  "quest_condition_40": "Type de rencontre",
  "quest_condition_41": "Gagne dans la Ligue Combat Go",
  "quest_condition_42": "Scanne un POI",
  "quest_condition_43": "Type d'objet",
  "quest_condition_44": "En moins de 10 Minutes",
  "quest_condition_44_formatted": "En %{time}s",
  "alignment_1": "Obscur",
  "alignment_2": "Purifié",
  "character_category_1": "Chef d'équipe",
  "character_category_2": "Sbire",
  "character_category_3": "Arlo",
  "character_category_4": "Cliff",
  "character_category_5": "Sierra",
  "character_category_6": "Giovanni",
  "character_category_9": "Event NPC",
  "throw_type_10": "Joli",
  "throw_type_11": "Super",
  "throw_type_12": "Excellent",
  "throw_type_13": "à effet",
  "grunt_0": "Aucun",
  "grunt_1": "Blanche",
  "grunt_2": "Candela",
  "grunt_3": "Spark",
  "grunt_4": "Sbire (mâle)",
  "grunt_5": "Sbire (femelle)",
  "grunt_6": "Insecte - Sbire (femelle)",
  "grunt_7": "Insecte - Sbire (mâle)",
  "grunt_8": "Spectre - Femelle Grunt",
  "grunt_9": "Spectre - Male Grunt",
  "grunt_10": "Ténèbres - Sbire (femelle)",
  "grunt_11": "Ténèbres - Sbire (mâle)",
  "grunt_12": "Dragon - Sbire (femelle)",
  "grunt_13": "Dragon - Sbire (mâle)",
  "grunt_14": "Fée - Sbire (femelle)",
  "grunt_15": "Fée - Sbire (mâle)",
  "grunt_16": "Combat - Sbire (femelle)",
  "grunt_17": "Combat - Sbire (mâle)",
  "grunt_18": "Feu - Sbire (femelle)",
  "grunt_19": "Feu - Sbire (mâle)",
  "grunt_20": "Vol - Sbire (femelle)",
  "grunt_21": "Vol - Sbire (mâle)",
  "grunt_22": "Plante - Sbire (femelle)",
  "grunt_23": "Plante - Sbire (mâle)",
  "grunt_24": "Sol - Sbire (femelle)",
  "grunt_25": "Sol - Sbire (mâle)",
  "grunt_26": "Glace - Sbire (femelle)",
  "grunt_27": "Glace - Sbire (mâle)",
  "grunt_28": "Sbire (femelle)",
  "grunt_29": "Sbire (mâle)",
  "grunt_30": "Normal - Sbire (femelle)",
  "grunt_31": "Normal - Sbire (mâle)",
  "grunt_32": "Poison - Sbire (femelle)",
  "grunt_33": "Poison - Sbire (mâle)",
  "grunt_34": "Psy - Sbire (femelle)",
  "grunt_35": "Psy - Sbire (mâle)",
  "grunt_36": "Roche - Sbire (femelle)",
  "grunt_37": "Roche - Sbire (mâle)",
  "grunt_38": "Eau - Sbire (femelle)",
  "grunt_39": "Eau - Sbire (mâle)",
  "grunt_40": "Blizzard",
  "grunt_41": "Chef Cliff",
  "grunt_42": "Chef Arlo",
  "grunt_43": "Chef Sierra",
  "grunt_44": "Giovanni",
  "grunt_45": "Faux Sbire (mâle)",
  "grunt_46": "Faux Sbire (femelle)",
  "grunt_47": "Spectre - Sbire (femelle)",
  "grunt_48": "Spectre - Sbire (mâle)",
  "grunt_49": "Électrik - Sbire (femelle)",
  "grunt_50": "Électrik - Sbire (mâle)",
  "gender_icon_0": "",
  "gender_icon_1": "♂",
  "gender_icon_2": "♀",
  "gender_icon_3": "⚲",
  "weather_icon_1": "☀️",
  "weather_icon_2": "☔️",
  "weather_icon_3": "⛅",
  "weather_icon_4": "☁️",
  "weather_icon_5": "💨",
  "weather_icon_6": "⛄️",
  "weather_icon_7": "🌁",
  "poke_0": "Pokémon",
  "item_0": "Inconnu",
  "raid_1": "Raid Niveau 1",
  "raid_1_plural": "Raids Niveau 1",
  "raid_2": "Raid Niveau 2",
  "raid_2_plural": "Raids Niveau 2",
  "raid_3": "Raid Niveau 3",
  "raid_3_plural": "Raids Niveau 3",
  "raid_4": "Raid Niveau 4",
  "raid_4_plural": "Raids Niveau 4",
  "raid_5": "Raid Légendaire",
  "raid_5_plural": "Raids Légendaires",
  "raid_6": "Raid Méga",
  "raid_6_plural": "Raids Méga",
  "raid_7": "Raid Méga Légendaire",
  "raid_7_plural": "Raids Méga Légendaires",
  "egg_1": "Œuf Niveau 1",
  "egg_1_plural": "Œufs Niveau 1",
  "egg_2": "Œuf Niveau 2",
  "egg_2_plural": "Œufs Niveau 2",
  "egg_3": "Œuf Niveau 3",
  "egg_3_plural": "Œufs Niveau 3",
  "egg_4": "Œuf Niveau 4",
  "egg_4_plural": "Œufs Niveau 4",
  "egg_5": "Œuf Légendaire",
  "egg_5_plural": "Œufs Légendaires",
  "egg_6": "Œuf Méga",
  "egg_6_plural": "Œufs Méga",
  "egg_7": "Œuf Méga Légendaire",
  "egg_7_plural": "Œufs Méga Légendaires"
}
